ArcREST_Package-3.5.9.dist-info/DESCRIPTION.rst
ArcREST_Package-3.5.9.dist-info/METADATA
ArcREST_Package-3.5.9.dist-info/RECORD
ArcREST_Package-3.5.9.dist-info/WHEEL
ArcREST_Package-3.5.9.dist-info/metadata.json
ArcREST_Package-3.5.9.dist-info/top_level.txt
ArcREST_Package-3.5.9.dist-info/zip-safe
arcrest/__init__.py
arcrest/constants.py
arcrest/_abstract/__init__.py
arcrest/_abstract/abstract.py
arcrest/agol/__init__.py
arcrest/agol/_uploads.py
arcrest/agol/services.py
arcrest/agol/helperservices/__init__.py
arcrest/agol/helperservices/analysis.py
arcrest/agol/helperservices/elevation.py
arcrest/agol/helperservices/geocoder.py
arcrest/agol/helperservices/hydrology.py
arcrest/ags/__init__.py
arcrest/ags/_geocodeservice.py
arcrest/ags/_geodataservice.py
arcrest/ags/_geoprocessing.py
arcrest/ags/_globeservice.py
arcrest/ags/_gpobjects.py
arcrest/ags/_imageservice.py
arcrest/ags/_mobileservice.py
arcrest/ags/_networkservice.py
arcrest/ags/_schematicsservice.py
arcrest/ags/_streamservice.py
arcrest/ags/_uploads.py
arcrest/ags/_vectortile.py
arcrest/ags/featureservice.py
arcrest/ags/layer.py
arcrest/ags/mapservice.py
arcrest/ags/server.py
arcrest/ags/services.py
arcrest/cmp/__init__.py
arcrest/cmp/community.py
arcrest/common/__init__.py
arcrest/common/domain.py
arcrest/common/errorhandlers.py
arcrest/common/filters.py
arcrest/common/find.py
arcrest/common/general.py
arcrest/common/geometry.py
arcrest/common/renderer.py
arcrest/common/servicedef.py
arcrest/common/spatial.py
arcrest/common/symbology.py
arcrest/enrichment/__countrycodes.csv
arcrest/enrichment/__datacollectionnames.csv
arcrest/enrichment/__init__.py
arcrest/enrichment/_geoenrichment.py
arcrest/geometryservice/__init__.py
arcrest/geometryservice/geometryservice.py
arcrest/hostedservice/__init__.py
arcrest/hostedservice/service.py
arcrest/manageags/__init__.py
arcrest/manageags/_clusters.py
arcrest/manageags/_data.py
arcrest/manageags/_info.py
arcrest/manageags/_kml.py
arcrest/manageags/_logs.py
arcrest/manageags/_machines.py
arcrest/manageags/_mode.py
arcrest/manageags/_security.py
arcrest/manageags/_services.py
arcrest/manageags/_system.py
arcrest/manageags/_uploads.py
arcrest/manageags/_usagereports.py
