Metadata-Version: 2.0
Name: ArcREST-Package
Version: 3.5.9
Summary: ArcREST is a Python Wrapper for the Esri REST Framework
Home-page: https://github.com/Esri/ArcREST
Author: Andrew Chapkowski, Mike Miller
Author-email: achapkowski@esri.com, mmiller@esri.com
License: Apache 2.0
Keywords: REST,Esri,ArcGIS,Python,ArcPy
Platform: UNKNOWN
Classifier: Development Status :: 5 - Production/Stable
Classifier: Intended Audience :: Developers
Classifier: Natural Language :: English
Classifier: License :: OSI Approved :: Apache Software License
Classifier: Programming Language :: Python
Classifier: Programming Language :: Python :: 2.6
Classifier: Programming Language :: Python :: 2.7
Classifier: Programming Language :: Python :: 3
Classifier: Programming Language :: Python :: 3.3
Classifier: Programming Language :: Python :: 3.4
Classifier: Programming Language :: Python :: 3.5
Classifier: Programming Language :: Python :: Implementation :: PyPy
Requires-Dist: numpy (>=1.7.1)
